printlistmodule.py
setup.py
printlistmodulepackageneeraj.egg-info/PKG-INFO
printlistmodulepackageneeraj.egg-info/SOURCES.txt
printlistmodulepackageneeraj.egg-info/dependency_links.txt
printlistmodulepackageneeraj.egg-info/top_level.txt