Metadata-Version: 1.0
Name: printlistmodulepackageneeraj
Version: 1.0.0
Summary: an API to print       a list recursively
Home-page: UNKNOWN
Author: Neeraj
Author-email: neeraj.pm@ignitarium.com
License: UNKNOWN
Platform: UNKNOWN
